lzprompt/__init__.py
lzprompt/cli.py
lzprompt-0.0.1.dist-info/LICENSE
lzprompt-0.0.1.dist-info/METADATA
lzprompt-0.0.1.dist-info/WHEEL
lzprompt-0.0.1.dist-info/entry_points.txt
lzprompt-0.0.1.dist-info/top_level.txt
lzprompt-0.0.1.dist-info/RECORD
