Metadata-Version: 2.2
Name: lzprompt
Version: 0.0.1
Summary: Lazy prompt building and response parsing.
Author-email: Ian Maurer <imaurer@gmail.com>
Project-URL: Homepage, https://lzkit.com/lzprompt/
Project-URL: Repository, https://github.com/lzkit/lzprompt
Project-URL: Documentation, https://lzkit.com/lzprompt/
Keywords: python
Classifier: Intended Audience :: Developers
Classifier: Programming Language :: Python
Classifier: Programming Language :: Python :: 3
Classifier: Programming Language :: Python :: 3.11
Classifier: Programming Language :: Python :: 3.12
Classifier: Programming Language :: Python :: 3.13
Classifier: Topic :: Software Development :: Libraries :: Python Modules
Requires-Python: <4.0,>=3.11
License-File: LICENSE
Requires-Dist: click>=8.1.8
Provides-Extra: api
